{"path": "/home/asumal/git/cs410/pattern/pattern/web/api.py", "lines": [[{"index": "1", "colour": "orange", "code": "#--- API LICENSE CONFIGURATION -----------------------------------------------------------------------\n", "error": "none", "author": "tom@organisms.be"}, {"index": "2", "colour": "orange", "code": "# Default license keys used by pattern.web.SearchEngine to contact different API's.\n", "error": "none", "author": "tom@organisms.be"}, {"index": "3", "colour": "orange", "code": "# Google and Yahoo are paid services for which you need a personal license + payment method.\n", "error": "none", "author": "tom@organisms.be"}, {"index": "4", "colour": "orange", "code": "# The default Google license is for testing purposes (= 100 daily queries).\n", "error": "none", "author": "tom@organisms.be"}, {"index": "5", "colour": "orange", "code": "# Wikipedia, Twitter and Facebook are free.\n", "error": "none", "author": "tom@organisms.be"}, {"index": "6", "colour": "orange", "code": "# Bing, Flickr and ProductsWiki use licenses shared among all Pattern users.\n", "error": "none", "author": "tom@organisms.be"}, {"index": "7", "colour": "orange", "code": "\n", "error": "none", "author": "tom@organisms.be"}, {"index": "8", "colour": "green", "code": "license = {}\n", "error": "W", "author": "tom@organisms.be"}, {"index": "9", "colour": "orange", "code": "license[\"Google\"] = \\\n", "error": "none", "author": "tom@organisms.be"}, {"index": "10", "colour": "orange", "code": "    \"AIzaSyBxe9jC4WLr-Rry_5OUMOZ7PCsEyWpiU48\"\n", "error": "none", "author": "tom@organisms.be"}, {"index": "11", "colour": "orange", "code": "\n", "error": "none", "author": "tom@organisms.be"}, {"index": "12", "colour": "orange", "code": "license[\"Bing\"] = \\\n", "error": "none", "author": "tom@organisms.be"}, {"index": "13", "colour": "orange", "code": "    \"VnJEK4HTlntE3SyF58QLkUCLp/78tkYjV1Fl3J7lHa0=\"\n", "error": "none", "author": "tom@organisms.be"}, {"index": "14", "colour": "orange", "code": "\n", "error": "none", "author": "tom@organisms.be"}, {"index": "15", "colour": "orange", "code": "license[\"Yahoo\"] = \\\n", "error": "none", "author": "tom@organisms.be"}, {"index": "16", "colour": "orange", "code": "    (\"\", \"\") # OAuth (key, secret)\n", "error": "none", "author": "tom@organisms.be"}, {"index": "17", "colour": "orange", "code": "\n", "error": "none", "author": "tom@organisms.be"}, {"index": "18", "colour": "orange", "code": "license[\"DuckDuckGo\"] = \\\n", "error": "none", "author": "tom@organisms.be"}, {"index": "19", "colour": "orange", "code": "    None\n", "error": "none", "author": "tom@organisms.be"}, {"index": "20", "colour": "orange", "code": "\n", "error": "none", "author": "tom@organisms.be"}, {"index": "21", "colour": "orange", "code": "license[\"Wikipedia\"] = \\\n", "error": "none", "author": "tom@organisms.be"}, {"index": "22", "colour": "orange", "code": "    None\n", "error": "none", "author": "tom@organisms.be"}, {"index": "23", "colour": "orange", "code": "\n", "error": "none", "author": "tom@organisms.be"}, {"index": "24", "colour": "orange", "code": "license[\"Twitter\"] = (\n", "error": "none", "author": "tom@organisms.be"}, {"index": "25", "colour": "orange", "code": "    \"p7HUdPLlkKaqlPn6TzKkA\", # OAuth (key, secret, token)\n", "error": "none", "author": "tom@organisms.be"}, {"index": "26", "colour": "orange", "code": "    \"R7I1LRuLY27EKjzulutov74lKB0FjqcI2DYRUmsu7DQ\", (\n", "error": "none", "author": "tom@organisms.be"}, {"index": "27", "colour": "orange", "code": "    \"14898655-TE9dXQLrzrNd0Zwf4zhK7koR5Ahqt40Ftt35Y2qY\",\n", "error": "none", "author": "tom@organisms.be"}, {"index": "28", "colour": "orange", "code": "    \"q1lSRDOguxQrfgeWWSJgnMHsO67bqTd5dTElBsyTM\"))\n", "error": "none", "author": "tom@organisms.be"}, {"index": "29", "colour": "orange", "code": "\n", "error": "none", "author": "tom@organisms.be"}, {"index": "30", "colour": "orange", "code": "license[\"Facebook\"] = \\\n", "error": "none", "author": "tom@organisms.be"}, {"index": "31", "colour": "orange", "code": "    \"332061826907464|jdHvL3lslFvN-s_sphK1ypCwNaY\"\n", "error": "none", "author": "tom@organisms.be"}, {"index": "32", "colour": "orange", "code": "\n", "error": "none", "author": "tom@organisms.be"}, {"index": "33", "colour": "orange", "code": "license[\"Flickr\"] = \\\n", "error": "none", "author": "tom@organisms.be"}, {"index": "34", "colour": "orange", "code": "    \"787081027f43b0412ba41142d4540480\"\n", "error": "none", "author": "tom@organisms.be"}, {"index": "35", "colour": "orange", "code": "\n", "error": "none", "author": "tom@organisms.be"}, {"index": "36", "colour": "orange", "code": "license[\"ProductWiki\"] = \\\n", "error": "none", "author": "tom@organisms.be"}, {"index": "37", "colour": "orange", "code": "    \"64819965ec784395a494a0d7ed0def32\"\n", "error": "none", "author": "tom@organisms.be"}]]}